[
  {
    "name": "Application Start",
    "start": 1578109520338,
    "end": 1578109523529,
    "duration": 3191,
    "pid": 16260,
    "index": 0
  },
  {
    "name": "Load Plugin",
    "start": 1578109520347,
    "end": 1578109520429,
    "duration": 82,
    "pid": 16260,
    "index": 1
  },
  {
    "name": "Load Config",
    "start": 1578109520429,
    "end": 1578109520484,
    "duration": 55,
    "pid": 16260,
    "index": 2
  },
  {
    "name": "Require(0) config/config.default.js",
    "start": 1578109520430,
    "end": 1578109520431,
    "duration": 1,
    "pid": 16260,
    "index": 3
  },
  {
    "name": "Require(1) node_modules/_egg-session@3.1.0@egg-session/config/config.default.js",
    "start": 1578109520434,
    "end": 1578109520435,
    "duration": 1,
    "pid": 16260,
    "index": 4
  },
  {
    "name": "Require(2) node_modules/_egg-security@2.7.1@egg-security/config/config.default.js",
    "start": 1578109520436,
    "end": 1578109520436,
    "duration": 0,
    "pid": 16260,
    "index": 5
  },
  {
    "name": "Require(3) node_modules/_egg-jsonp@2.0.0@egg-jsonp/config/config.default.js",
    "start": 1578109520438,
    "end": 1578109520438,
    "duration": 0,
    "pid": 16260,
    "index": 6
  },
  {
    "name": "Require(4) node_modules/_egg-onerror@2.1.0@egg-onerror/config/config.default.js",
    "start": 1578109520440,
    "end": 1578109520440,
    "duration": 0,
    "pid": 16260,
    "index": 7
  },
  {
    "name": "Require(5) node_modules/_egg-i18n@2.1.1@egg-i18n/config/config.default.js",
    "start": 1578109520441,
    "end": 1578109520442,
    "duration": 1,
    "pid": 16260,
    "index": 8
  },
  {
    "name": "Require(6) node_modules/_egg-watcher@3.1.0@egg-watcher/config/config.default.js",
    "start": 1578109520443,
    "end": 1578109520443,
    "duration": 0,
    "pid": 16260,
    "index": 9
  },
  {
    "name": "Require(7) node_modules/_egg-schedule@3.6.4@egg-schedule/config/config.default.js",
    "start": 1578109520445,
    "end": 1578109520445,
    "duration": 0,
    "pid": 16260,
    "index": 10
  },
  {
    "name": "Require(8) node_modules/_egg-multipart@2.10.1@egg-multipart/config/config.default.js",
    "start": 1578109520446,
    "end": 1578109520447,
    "duration": 1,
    "pid": 16260,
    "index": 11
  },
  {
    "name": "Require(9) node_modules/_egg-development@2.4.3@egg-development/config/config.default.js",
    "start": 1578109520448,
    "end": 1578109520451,
    "duration": 3,
    "pid": 16260,
    "index": 12
  },
  {
    "name": "Require(10) node_modules/_egg-logrotator@3.1.0@egg-logrotator/config/config.default.js",
    "start": 1578109520452,
    "end": 1578109520453,
    "duration": 1,
    "pid": 16260,
    "index": 13
  },
  {
    "name": "Require(11) node_modules/_egg-static@2.2.0@egg-static/config/config.default.js",
    "start": 1578109520454,
    "end": 1578109520454,
    "duration": 0,
    "pid": 16260,
    "index": 14
  },
  {
    "name": "Require(12) node_modules/_egg-view@2.1.2@egg-view/config/config.default.js",
    "start": 1578109520455,
    "end": 1578109520456,
    "duration": 1,
    "pid": 16260,
    "index": 15
  },
  {
    "name": "Require(13) node_modules/_egg-mongoose@3.2.0@egg-mongoose/config/config.default.js",
    "start": 1578109520459,
    "end": 1578109520460,
    "duration": 1,
    "pid": 16260,
    "index": 16
  },
  {
    "name": "Require(14) node_modules/_egg-view-ejs@2.0.0@egg-view-ejs/config/config.default.js",
    "start": 1578109520461,
    "end": 1578109520461,
    "duration": 0,
    "pid": 16260,
    "index": 17
  },
  {
    "name": "Require(15) node_modules/_egg-jwt@3.1.7@egg-jwt/config/config.default.js",
    "start": 1578109520463,
    "end": 1578109520463,
    "duration": 0,
    "pid": 16260,
    "index": 18
  },
  {
    "name": "Require(16) node_modules/_egg@2.26.0@egg/config/config.default.js",
    "start": 1578109520464,
    "end": 1578109520465,
    "duration": 1,
    "pid": 16260,
    "index": 19
  },
  {
    "name": "Require(17) config/config.default.js",
    "start": 1578109520466,
    "end": 1578109520466,
    "duration": 0,
    "pid": 16260,
    "index": 20
  },
  {
    "name": "Require(18) node_modules/_egg-security@2.7.1@egg-security/config/config.local.js",
    "start": 1578109520468,
    "end": 1578109520468,
    "duration": 0,
    "pid": 16260,
    "index": 21
  },
  {
    "name": "Require(19) node_modules/_egg-watcher@3.1.0@egg-watcher/config/config.local.js",
    "start": 1578109520472,
    "end": 1578109520472,
    "duration": 0,
    "pid": 16260,
    "index": 22
  },
  {
    "name": "Require(20) node_modules/_egg-view@2.1.2@egg-view/config/config.local.js",
    "start": 1578109520478,
    "end": 1578109520478,
    "duration": 0,
    "pid": 16260,
    "index": 23
  },
  {
    "name": "Require(21) node_modules/_egg-view-ejs@2.0.0@egg-view-ejs/config/config.local.js",
    "start": 1578109520480,
    "end": 1578109520481,
    "duration": 1,
    "pid": 16260,
    "index": 24
  },
  {
    "name": "Require(22) node_modules/_egg@2.26.0@egg/config/config.local.js",
    "start": 1578109520483,
    "end": 1578109520484,
    "duration": 1,
    "pid": 16260,
    "index": 25
  },
  {
    "name": "Load extend/application.js",
    "start": 1578109520485,
    "end": 1578109520724,
    "duration": 239,
    "pid": 16260,
    "index": 26
  },
  {
    "name": "Require(23) node_modules/_egg-session@3.1.0@egg-session/app/extend/application.js",
    "start": 1578109520487,
    "end": 1578109520488,
    "duration": 1,
    "pid": 16260,
    "index": 27
  },
  {
    "name": "Require(24) node_modules/_egg-security@2.7.1@egg-security/app/extend/application.js",
    "start": 1578109520489,
    "end": 1578109520492,
    "duration": 3,
    "pid": 16260,
    "index": 28
  },
  {
    "name": "Require(25) node_modules/_egg-jsonp@2.0.0@egg-jsonp/app/extend/application.js",
    "start": 1578109520494,
    "end": 1578109520500,
    "duration": 6,
    "pid": 16260,
    "index": 29
  },
  {
    "name": "Require(26) node_modules/_egg-logrotator@3.1.0@egg-logrotator/app/extend/application.js",
    "start": 1578109520507,
    "end": 1578109520516,
    "duration": 9,
    "pid": 16260,
    "index": 30
  },
  {
    "name": "Require(27) node_modules/_egg-view@2.1.2@egg-view/app/extend/application.js",
    "start": 1578109520518,
    "end": 1578109520524,
    "duration": 6,
    "pid": 16260,
    "index": 31
  },
  {
    "name": "Require(28) node_modules/_egg-jwt@3.1.7@egg-jwt/app/extend/application.js",
    "start": 1578109520527,
    "end": 1578109520704,
    "duration": 177,
    "pid": 16260,
    "index": 32
  },
  {
    "name": "Load extend/request.js",
    "start": 1578109520724,
    "end": 1578109520761,
    "duration": 37,
    "pid": 16260,
    "index": 33
  },
  {
    "name": "Require(29) node_modules/_egg@2.26.0@egg/app/extend/request.js",
    "start": 1578109520739,
    "end": 1578109520744,
    "duration": 5,
    "pid": 16260,
    "index": 34
  },
  {
    "name": "Load extend/response.js",
    "start": 1578109520761,
    "end": 1578109520808,
    "duration": 47,
    "pid": 16260,
    "index": 35
  },
  {
    "name": "Require(30) node_modules/_egg@2.26.0@egg/app/extend/response.js",
    "start": 1578109520774,
    "end": 1578109520782,
    "duration": 8,
    "pid": 16260,
    "index": 36
  },
  {
    "name": "Load extend/context.js",
    "start": 1578109520808,
    "end": 1578109520978,
    "duration": 170,
    "pid": 16260,
    "index": 37
  },
  {
    "name": "Require(31) node_modules/_egg-security@2.7.1@egg-security/app/extend/context.js",
    "start": 1578109520810,
    "end": 1578109520853,
    "duration": 43,
    "pid": 16260,
    "index": 38
  },
  {
    "name": "Require(32) node_modules/_egg-jsonp@2.0.0@egg-jsonp/app/extend/context.js",
    "start": 1578109520854,
    "end": 1578109520858,
    "duration": 4,
    "pid": 16260,
    "index": 39
  },
  {
    "name": "Require(33) node_modules/_egg-i18n@2.1.1@egg-i18n/app/extend/context.js",
    "start": 1578109520860,
    "end": 1578109520860,
    "duration": 0,
    "pid": 16260,
    "index": 40
  },
  {
    "name": "Require(34) node_modules/_egg-multipart@2.10.1@egg-multipart/app/extend/context.js",
    "start": 1578109520863,
    "end": 1578109520948,
    "duration": 85,
    "pid": 16260,
    "index": 41
  },
  {
    "name": "Require(35) node_modules/_egg-view@2.1.2@egg-view/app/extend/context.js",
    "start": 1578109520951,
    "end": 1578109520954,
    "duration": 3,
    "pid": 16260,
    "index": 42
  },
  {
    "name": "Require(36) node_modules/_egg-mongoose@3.2.0@egg-mongoose/app/extend/context.js",
    "start": 1578109520955,
    "end": 1578109520956,
    "duration": 1,
    "pid": 16260,
    "index": 43
  },
  {
    "name": "Require(37) node_modules/_egg@2.26.0@egg/app/extend/context.js",
    "start": 1578109520958,
    "end": 1578109520962,
    "duration": 4,
    "pid": 16260,
    "index": 44
  },
  {
    "name": "Load extend/helper.js",
    "start": 1578109520978,
    "end": 1578109521064,
    "duration": 86,
    "pid": 16260,
    "index": 45
  },
  {
    "name": "Require(38) node_modules/_egg-security@2.7.1@egg-security/app/extend/helper.js",
    "start": 1578109520980,
    "end": 1578109521031,
    "duration": 51,
    "pid": 16260,
    "index": 46
  },
  {
    "name": "Require(39) node_modules/_egg@2.26.0@egg/app/extend/helper.js",
    "start": 1578109521042,
    "end": 1578109521043,
    "duration": 1,
    "pid": 16260,
    "index": 47
  },
  {
    "name": "Require(40) app/extend/helper.js",
    "start": 1578109521044,
    "end": 1578109521051,
    "duration": 7,
    "pid": 16260,
    "index": 48
  },
  {
    "name": "Load app.js",
    "start": 1578109521064,
    "end": 1578109521188,
    "duration": 124,
    "pid": 16260,
    "index": 49
  },
  {
    "name": "Require(41) node_modules/_egg-session@3.1.0@egg-session/app.js",
    "start": 1578109521065,
    "end": 1578109521066,
    "duration": 1,
    "pid": 16260,
    "index": 50
  },
  {
    "name": "Require(42) node_modules/_egg-security@2.7.1@egg-security/app.js",
    "start": 1578109521067,
    "end": 1578109521073,
    "duration": 6,
    "pid": 16260,
    "index": 51
  },
  {
    "name": "Require(43) node_modules/_egg-onerror@2.1.0@egg-onerror/app.js",
    "start": 1578109521075,
    "end": 1578109521113,
    "duration": 38,
    "pid": 16260,
    "index": 52
  },
  {
    "name": "Require(44) node_modules/_egg-i18n@2.1.1@egg-i18n/app.js",
    "start": 1578109521115,
    "end": 1578109521142,
    "duration": 27,
    "pid": 16260,
    "index": 53
  },
  {
    "name": "Require(45) node_modules/_egg-watcher@3.1.0@egg-watcher/app.js",
    "start": 1578109521144,
    "end": 1578109521155,
    "duration": 11,
    "pid": 16260,
    "index": 54
  },
  {
    "name": "Require(46) node_modules/_egg-schedule@3.6.4@egg-schedule/app.js",
    "start": 1578109521156,
    "end": 1578109521162,
    "duration": 6,
    "pid": 16260,
    "index": 55
  },
  {
    "name": "Require(47) node_modules/_egg-multipart@2.10.1@egg-multipart/app.js",
    "start": 1578109521163,
    "end": 1578109521175,
    "duration": 12,
    "pid": 16260,
    "index": 56
  },
  {
    "name": "Require(48) node_modules/_egg-development@2.4.3@egg-development/app.js",
    "start": 1578109521176,
    "end": 1578109521176,
    "duration": 0,
    "pid": 16260,
    "index": 57
  },
  {
    "name": "Require(49) node_modules/_egg-logrotator@3.1.0@egg-logrotator/app.js",
    "start": 1578109521177,
    "end": 1578109521177,
    "duration": 0,
    "pid": 16260,
    "index": 58
  },
  {
    "name": "Require(50) node_modules/_egg-static@2.2.0@egg-static/app.js",
    "start": 1578109521178,
    "end": 1578109521179,
    "duration": 1,
    "pid": 16260,
    "index": 59
  },
  {
    "name": "Require(51) node_modules/_egg-mongoose@3.2.0@egg-mongoose/app.js",
    "start": 1578109521181,
    "end": 1578109521182,
    "duration": 1,
    "pid": 16260,
    "index": 60
  },
  {
    "name": "Require(52) node_modules/_egg-view-ejs@2.0.0@egg-view-ejs/app.js",
    "start": 1578109521183,
    "end": 1578109521183,
    "duration": 0,
    "pid": 16260,
    "index": 61
  },
  {
    "name": "Require(53) node_modules/_egg-jwt@3.1.7@egg-jwt/app.js",
    "start": 1578109521184,
    "end": 1578109521185,
    "duration": 1,
    "pid": 16260,
    "index": 62
  },
  {
    "name": "Before Start in node_modules/_egg-watcher@3.1.0@egg-watcher/lib/init.js:15:14",
    "start": 1578109521207,
    "end": 1578109523526,
    "duration": 2319,
    "pid": 16260,
    "index": 63
  },
  {
    "name": "Before Start in node_modules/_egg-mongoose@3.2.0@egg-mongoose/lib/mongoose.js:91:7",
    "start": 1578109522306,
    "end": 1578109523522,
    "duration": 1216,
    "pid": 16260,
    "index": 64
  },
  {
    "name": "Before Start in node_modules/_egg-mongoose@3.2.0@egg-mongoose/lib/mongoose.js:49:9",
    "start": 1578109522306,
    "end": 1578109523481,
    "duration": 1175,
    "pid": 16260,
    "index": 65
  },
  {
    "name": "Load Service",
    "start": 1578109522320,
    "end": 1578109523096,
    "duration": 776,
    "pid": 16260,
    "index": 66
  },
  {
    "name": "Load \"service\" to Context",
    "start": 1578109522320,
    "end": 1578109523096,
    "duration": 776,
    "pid": 16260,
    "index": 67
  },
  {
    "name": "Load Middleware",
    "start": 1578109523096,
    "end": 1578109523380,
    "duration": 284,
    "pid": 16260,
    "index": 68
  },
  {
    "name": "Load \"middlewares\" to Application",
    "start": 1578109523096,
    "end": 1578109523359,
    "duration": 263,
    "pid": 16260,
    "index": 69
  },
  {
    "name": "Load Controller",
    "start": 1578109523380,
    "end": 1578109523412,
    "duration": 32,
    "pid": 16260,
    "index": 70
  },
  {
    "name": "Load \"controller\" to Application",
    "start": 1578109523380,
    "end": 1578109523412,
    "duration": 32,
    "pid": 16260,
    "index": 71
  },
  {
    "name": "Load Router",
    "start": 1578109523412,
    "end": 1578109523418,
    "duration": 6,
    "pid": 16260,
    "index": 72
  },
  {
    "name": "Require(54) app/router.js",
    "start": 1578109523413,
    "end": 1578109523414,
    "duration": 1,
    "pid": 16260,
    "index": 73
  },
  {
    "name": "Before Start in node_modules/_egg-core@4.17.4@egg-core/lib/egg.js:303:10",
    "start": 1578109523416,
    "end": 1578109523481,
    "duration": 65,
    "pid": 16260,
    "index": 74
  },
  {
    "name": "Load \"model\" to Application",
    "start": 1578109523432,
    "end": 1578109523480,
    "duration": 48,
    "pid": 16260,
    "index": 75
  }
]